setup.py
django_tracware.egg-info/PKG-INFO
django_tracware.egg-info/SOURCES.txt
django_tracware.egg-info/dependency_links.txt
django_tracware.egg-info/top_level.txt
tracware/__init__.py
tracware/admin.py
tracware/apps.py
tracware/defaults.py
tracware/models.py
tracware/signals.py
tracware/urls.py
tracware/utils.py
tracware/views.py
tracware/migrations/0001_initial.py
tracware/migrations/0002_auto_20160206_1911.py
tracware/migrations/__init__.py
tracware/templatetags/__init__.py
tracware/templatetags/track.py
tracware/tests/__init__.py
tracware/tests/tests_trac.py
tracware/tests/testsettings.py